ncon_torch/__init__.py
ncon_torch/backend.py
ncon_torch/ncon.py
ncon_torch-0.3.0.dist-info/licenses/LICENSE
ncon_torch-0.3.0.dist-info/METADATA
ncon_torch-0.3.0.dist-info/WHEEL
ncon_torch-0.3.0.dist-info/top_level.txt
ncon_torch-0.3.0.dist-info/RECORD
