Metadata-Version: 2.4
Name: ncon-torch
Version: 0.3.0
Summary: Tensor network contraction function with GPU and autograd support via PyTorch.
Home-page: https://github.com/alam-faisal/ncon-torch
Author: Faisal Alam
Author-email: mfalam2@illinois.edu
License: MIT
Keywords: tensor networks
Classifier: Programming Language :: Python :: 3
Classifier: License :: OSI Approved :: MIT License
Classifier: Operating System :: OS Independent
Classifier: Topic :: Scientific/Engineering
Requires-Python: >=3.8
License-File: LICENSE
Requires-Dist: torch>=1.12
Requires-Dist: numpy>=1.20
Provides-Extra: tests
Requires-Dist: pytest; extra == "tests"
Requires-Dist: coverage; extra == "tests"
Requires-Dist: pytest-cov; extra == "tests"
Dynamic: author
Dynamic: author-email
Dynamic: classifier
Dynamic: description
Dynamic: description-content-type
Dynamic: home-page
Dynamic: keywords
Dynamic: license
Dynamic: license-file
Dynamic: provides-extra
Dynamic: requires-dist
Dynamic: requires-python
Dynamic: summary
